falcon_marshmallow/__init__.py
falcon_marshmallow/_version.py
falcon_marshmallow/middleware.py
falcon_marshmallow-0.3.0.dist-info/LICENSE
falcon_marshmallow-0.3.0.dist-info/METADATA
falcon_marshmallow-0.3.0.dist-info/WHEEL
falcon_marshmallow-0.3.0.dist-info/top_level.txt
falcon_marshmallow-0.3.0.dist-info/RECORD
