Metadata-Version: 2.1
Name: falcon-marshmallow
Version: 0.3.0
Summary: Automatic Marshmallow (De)serialization in Falcon
Home-page: https://www.github.com/mplanchard/falcon-marshmallow
Author: Matthew Planchard
Author-email: msplanchard@gmail.com
License: UNKNOWN
Keywords: ihiji,falcon,marshmallow,marshalling,middleware,serialization,deserialization,json,wsgi
Platform: UNKNOWN
Classifier: Development Status :: 5 - Production/Stable
Classifier: Environment :: Web Environment
Classifier: Intended Audience :: Developers
Classifier: License :: OSI Approved :: MIT License
Classifier: Natural Language :: English
Classifier: Operating System :: POSIX :: Linux
Classifier: Programming Language :: Python
Classifier: Programming Language :: Python :: 2
Classifier: Programming Language :: Python :: 2.7
Classifier: Programming Language :: Python :: 3
Classifier: Programming Language :: Python :: 3.4
Classifier: Programming Language :: Python :: 3.5
Classifier: Programming Language :: Python :: 3.6
Classifier: Programming Language :: Python :: 3.7
Classifier: Programming Language :: Python :: Implementation :: CPython
Classifier: Topic :: Internet :: WWW/HTTP :: WSGI :: Middleware
Requires-Dist: falcon
Requires-Dist: marshmallow
Requires-Dist: simplejson
Requires-Dist: typing ; python_version < "3.5"
